{"Dock Verified": [{"Current State": "Dock Verified", "Outputs": {}, "Next State": "Dock Verified", "Inputs": {}}], "Verifying": [{"Current State": "Verifying", "Outputs": {"angle": 0.0, "level": 0.0}, "Next State": "Dock Verified", "Inputs": {"Dock Left": "1", "Dock Right": "1", "Rear": "< 20", "Volts": ">=  12.8"}}, {"Current State": "Verifying", "Outputs": {"duration": -10.0, "angle": 0.0, "level": 0.0}, "Next State": "Verifying", "Inputs": {"Dock Left": "1", "Dock Right": "1", "Rear": "< 20", "Volts": "< 12.8"}}], "Approaching": [{"Current State": "Approaching", "Outputs": {"sensor": "Forward", "angle": 0.0, "range": 40.0, "level": 0.2}, "Next State": "Dock Orientation", "Inputs": {"Forward": "<= 215", "Right": "20:40", "heading": "330:345"}}, {"Current State": "Approaching", "Outputs": {"heading": 336.0}, "Next State": "Approaching", "Inputs": {"heading": "< 330"}}, {"Current State": "Approaching", "Outputs": {"heading": 336.0}, "Next State": "Approaching", "Inputs": {"heading": "> 345"}}, {"Current State": "Approaching", "Outputs": {}, "Next State": "Dock Failed", "Inputs": {"Forward": "> 215"}}], "Way Point 1": [{"Current State": "Way Point 1", "Outputs": {"sensor": "Forward", "angle": 0.0, "range": 40.0, "level": 0.2}, "Next State": "Facing Dock", "Inputs": {"Forward": "< 255", "heading": "85:100"}}, {"Current State": "Way Point 1", "Outputs": {}, "Next State": "Initial Orientation", "Inputs": {"heading": "> 100"}}, {"Current State": "Way Point 1", "Outputs": {}, "Next State": "Initial Orientation", "Inputs": {"heading": "< 85"}}, {"Current State": "Way Point 1", "Outputs": {}, "Next State": "Dock Failed", "Inputs": {"Forward": ">= 255"}}], "Contact": [{"Current State": "Contact", "Outputs": {"angle": 0.0, "level": 0.0}, "Next State": "Verifying", "Inputs": {"Amps Left": "<= -5.1", "Amps Right": "<= -5.1", "Dock Left": "1", "Dock Right": "1"}}, {"Current State": "Contact", "Outputs": {}, "Next State": "Verifying", "Inputs": {"Amps Left": "0", "Amps Right": "0", "Dock Right": "1", "Rear": "< 20", "Dock Left": "1", "Volts": ">= 12.8"}}, {"Current State": "Contact", "Outputs": {}, "Next State": "Signal Lock", "Inputs": {"Dock Right": "1", "Amps Left": "0", "Amps Right": "0", "Dock Left": "1", "Rear": ">=20"}}], "Signal Lock": [{"Current State": "Signal Lock", "Outputs": {"duration": 5.0, "angle": 180.0, "level": 0.25}, "Next State": "Contact", "Inputs": {"Dock Left": "1", "heading": "176:184", "Dock Right": "1"}}, {"Current State": "Signal Lock", "Outputs": {"heading": 180.0}, "Next State": "Signal Lock", "Inputs": {"heading": "< 176"}}, {"Current State": "Signal Lock", "Outputs": {"heading": 180.0}, "Next State": "Signal Lock", "Inputs": {"heading": "> 184"}}], "Dock Orientation": [{"Current State": "Dock Orientation", "Outputs": {"heading": 180.0}, "Next State": "Signal Lock", "Inputs": {"Forward": "39:41"}}, {"Current State": "Dock Orientation", "Outputs": {"sensor": "Forward", "angle": 180.0, "range": 40.0, "level": 0.2}, "Next State": "Dock Orientation", "Inputs": {"Forward": "< 39"}}, {"Current State": "Dock Orientation", "Outputs": {"sensor": "Forward", "angle": 0.0, "range": 40.0, "level": 0.2}, "Next State": "Dock Orientation", "Inputs": {"Forward": "> 41"}}], "Initial Orientation": [{"Current State": "Initial Orientation", "Outputs": {"heading": 95.0}, "Next State": "Way Point 1", "Inputs": {}}], "Facing Dock": [{"Current State": "Facing Dock", "Outputs": {"heading": 336.0}, "Next State": "Approaching", "Inputs": {"Forward": "39:41"}}, {"Current State": "Facing Dock", "Outputs": {"sensor": "Forward", "angle": 180.0, "range": 40.0, "level": 0.2}, "Next State": "Facing Dock", "Inputs": {"Forward": "< 39"}}, {"Current State": "Facing Dock", "Outputs": {"sensor": "Forward", "angle": 0.0, "range": 40.0, "level": 0.2}, "Next State": "Facing Dock", "Inputs": {"Forward": "> 41"}}], "Dock Failed": [{"Current State": "Dock Failed", "Outputs": {}, "Next State": "Dock Failed", "Inputs": {"Volts": "<=  12.7"}}]}